LICENSE.txt
README.md
setup.cfg
setup.py
krrsnkapi/__init__.py
krrsnkapi/krrsnkapi.py
krrsnkapi.egg-info/PKG-INFO
krrsnkapi.egg-info/SOURCES.txt
krrsnkapi.egg-info/dependency_links.txt
krrsnkapi.egg-info/requires.txt
krrsnkapi.egg-info/top_level.txt