Metadata-Version: 2.1
Name: krrsnkapi
Version: 0.3.1
Summary: Module for easy use of my api | info on GitHub: https://github.com/kararasenok-gd/krrsnkapi
Home-page: https://github.com/kararasenok-gd/krrsnkapi
Download-URL: https://github.com/kararasenok-gd/krrsnkapi/archive/v0.3.tar.gz
Author: kararasenok_gd
Author-email: murzikkurzikpro@gmail.com
License: MIT
Keywords: api
Classifier: Development Status :: 4 - Beta
Classifier: Topic :: Software Development :: Build Tools
Classifier: License :: OSI Approved :: MIT License
Classifier: Programming Language :: Python :: 3.8
License-File: LICENSE.txt
